maskstr/__init__.py
maskstr-0.0.1.dist-info/LICENSE
maskstr-0.0.1.dist-info/METADATA
maskstr-0.0.1.dist-info/WHEEL
maskstr-0.0.1.dist-info/top_level.txt
maskstr-0.0.1.dist-info/RECORD
