Metadata-Version: 2.1
Name: maskstr
Version: 0.0.1
Summary: string masking
Home-page: https://github.com/marco-ostaska/stamaskstr
Author: Marco Ostaska
Author-email: marcoan@ymail.com
License: UNKNOWN
Platform: UNKNOWN
Classifier: Programming Language :: Python :: 3.7
Classifier: License :: OSI Approved :: MIT License
Classifier: Operating System :: OS Independent
